procpipe/__init__.py
procpipe/pipeline.py
procpipe-2020.10.dist-info/LICENSE
procpipe-2020.10.dist-info/METADATA
procpipe-2020.10.dist-info/WHEEL
procpipe-2020.10.dist-info/top_level.txt
procpipe-2020.10.dist-info/RECORD
