Metadata-Version: 2.1
Name: procpipe
Version: 2020.10
Summary: Simple data processing pipelines
Home-page: https://github.com/cdaudt/pipeline
Author: Christian Daudt
Author-email: csd@fixthebug.org
License: UNKNOWN
Platform: UNKNOWN
Classifier: Programming Language :: Python :: 3
Classifier: License :: OSI Approved :: MIT License
Classifier: Operating System :: OS Independent
Requires-Python: >=3.6
